potnanny/__init__.py
potnanny/app.py
potnanny/ble.py
potnanny/cli.py
potnanny/config.py
potnanny/database.py
potnanny/api/__init__.py
potnanny/api/about/__init__.py
potnanny/api/about/views.py
potnanny/api/about/templates/__init__.py
potnanny/api/about/templates/about/__init__.py
potnanny/api/about/templates/about/index.html
potnanny/api/actions/__init__.py
potnanny/api/actions/views.py
potnanny/api/actions/templates/__init__.py
potnanny/api/actions/templates/actions/__init__.py
potnanny/api/actions/templates/actions/index.html
potnanny/api/auth/__init__.py
potnanny/api/auth/forms.py
potnanny/api/auth/views.py
potnanny/api/auth/templates/__init__.py
potnanny/api/auth/templates/auth/__init__.py
potnanny/api/auth/templates/auth/login.html
potnanny/api/auth/templates/auth/reset.html
potnanny/api/controls/__init__.py
potnanny/api/controls/views.py
potnanny/api/devices/__init__.py
potnanny/api/devices/views.py
potnanny/api/devices/templates/__init__.py
potnanny/api/devices/templates/devices/__init__.py
potnanny/api/devices/templates/devices/index.html
potnanny/api/environments/__init__.py
potnanny/api/environments/controllers.py
potnanny/api/environments/views.py
potnanny/api/environments/templates/__init__.py
potnanny/api/environments/templates/environments/__init__.py
potnanny/api/environments/templates/environments/dash.html
potnanny/api/environments/templates/environments/room.html
potnanny/api/errors/__init__.py
potnanny/api/errors/controllers.py
potnanny/api/errors/views.py
potnanny/api/errors/templates/__init__.py
potnanny/api/errors/templates/errors/__init__.py
potnanny/api/errors/templates/errors/index.html
potnanny/api/features/__init__.py
potnanny/api/features/controllers.py
potnanny/api/features/forms.py
potnanny/api/features/views.py
potnanny/api/features/templates/__init__.py
potnanny/api/features/templates/features/__init__.py
potnanny/api/features/templates/features/form.html
potnanny/api/features/templates/features/index.html
potnanny-0.5.6.dist-info/LICENSE
potnanny-0.5.6.dist-info/METADATA
potnanny-0.5.6.dist-info/WHEEL
potnanny-0.5.6.dist-info/entry_points.txt
potnanny-0.5.6.dist-info/top_level.txt
potnanny-0.5.6.dist-info/RECORD
