Metadata-Version: 2.1
Name: potnanny
Version: 0.5.6
Summary: Potnanny grow room automation controller.
Home-page: https://github.com/potnanny/application
Author: J Leary
Author-email: potnanny@gmail.com
Requires-Python: >=3.11
License-File: LICENSE
Requires-Dist: greenlet
Requires-Dist: bleak
Requires-Dist: aio-databases[aiosqlite]
Requires-Dist: aiosmtplib
Requires-Dist: aiofiles
Requires-Dist: peewee-aio
Requires-Dist: quart
Requires-Dist: quart-auth
Requires-Dist: quart-wtforms
Requires-Dist: pyyaml
Requires-Dist: gpiozero
Requires-Dist: marshmallow
Requires-Dist: python-daemon
Requires-Dist: markupsafe
Requires-Dist: cryptography
Requires-Dist: jsmin
